filehandlr/__init__.py
filehandlr/__main__.py
filehandlr-0.1.dist-info/METADATA
filehandlr-0.1.dist-info/WHEEL
filehandlr-0.1.dist-info/top_level.txt
filehandlr-0.1.dist-info/RECORD
